qface/__about__.py
qface/__init__.py
qface/app.py
qface/cli.py
qface/filters.py
qface/generator.py
qface/shell.py
qface/utils.py
qface/watch.py
qface/contrib/__init__.py
qface/contrib/logging.py
qface/helper/__init__.py
qface/helper/doc.py
qface/helper/generic.py
qface/helper/qtcpp.py
qface/helper/qtqml.py
qface/idl/__init__.py
qface/idl/domain.py
qface/idl/listener.py
qface/idl/profile.py
qface/idl/parser/T4Lexer.py
qface/idl/parser/T4Listener.py
qface/idl/parser/T4Parser.py
qface/idl/parser/TLexer.py
qface/idl/parser/TListener.py
qface/idl/parser/TParser.py
qface/idl/parser/TVisitor.py
qface/idl/parser/__init__.py
qface/templates/qface/qtcpp.j2
qface-2.0.13.dist-info/LICENSE
qface-2.0.13.dist-info/METADATA
qface-2.0.13.dist-info/WHEEL
qface-2.0.13.dist-info/entry_points.txt
qface-2.0.13.dist-info/top_level.txt
qface-2.0.13.dist-info/RECORD
