Metadata-Version: 2.1
Name: qface
Version: 2.0.13
Summary: A generator framework based on a common modern IDL
Home-page: UNKNOWN
Author: JRyannel
Author-email: 
License: MIT
Keywords: qt code generator framework
Platform: UNKNOWN
Classifier: Development Status :: 5 - Production/Stable
Classifier: Intended Audience :: Developers
Classifier: Topic :: Software Development :: Code Generators
Classifier: License :: OSI Approved :: MIT License
Classifier: Programming Language :: Python :: 3
Requires-Python: >=3.5
Requires-Dist: click >=6.7
Requires-Dist: antlr4-python3-runtime >=4.7.1
Requires-Dist: jinja2 >=2.10.3
Requires-Dist: pyyaml >=5.1
Requires-Dist: watchdog >=1.0
Requires-Dist: six >=1.11.0
Requires-Dist: coloredlogs >=10.0
Provides-Extra: dev
Requires-Dist: watchdog ; extra == 'dev'
Requires-Dist: pypandoc ; extra == 'dev'
Provides-Extra: test
Requires-Dist: pytest ; extra == 'test'
Requires-Dist: watchdog ; extra == 'test'
Requires-Dist: ipdb ; extra == 'test'
